skyagent/__init__.py
skyagent/core.py
skyagent/repl/__init__.py
skyagent/repl/repl.py
skyagent/types.py
skyagent/util.py
skyagent_python-0.2.0.dist-info/METADATA
skyagent_python-0.2.0.dist-info/WHEEL
skyagent_python-0.2.0.dist-info/RECORD
