Metadata-Version: 2.1
Name: skyagent-python
Version: 0.2.0
Summary: a tool to manage LAE agent
Author: jerry zhang
Author-email: jerry.zhang@peopleaviation.net
Requires-Python: >=3.10,<4.0
Classifier: Programming Language :: Python :: 3
Classifier: Programming Language :: Python :: 3.10
Classifier: Programming Language :: Python :: 3.11
Classifier: Programming Language :: Python :: 3.12
Requires-Dist: pytest (>=8.3.3,<9.0.0)
